armangrewal007/__init__.py
armangrewal007/cli.py
armangrewal007-0.1.3.dist-info/LICENSE
armangrewal007-0.1.3.dist-info/METADATA
armangrewal007-0.1.3.dist-info/WHEEL
armangrewal007-0.1.3.dist-info/entry_points.txt
armangrewal007-0.1.3.dist-info/top_level.txt
armangrewal007-0.1.3.dist-info/RECORD
