Metadata-Version: 2.1
Name: armangrewal007
Version: 0.1.3
Summary: A CLI to display Arman Singh Grewal's resume
Home-page: https://github.com/armangrewal007
Author: Arman Singh Grewal
Author-email: Arman Singh Grewal <armancode4u@gmail.com>
License: MIT
Requires-Python: >=3.8
License-File: LICENSE
Requires-Dist: rich
